orangecontrib.earth-0.1.4-py2.7-nspkg.pth
orangecontrib/earth/__init__.py
orangecontrib/earth/_earth.so
orangecontrib/earth/core.py
orangecontrib/earth/earth.py
orangecontrib/earth/evimp.py
orangecontrib/earth/tests/__init__.py
orangecontrib/earth/tests/test_core.py
orangecontrib/earth/tests/test_earth.py
orangecontrib/earth/widgets/OWEarth.py
orangecontrib/earth/widgets/__init__.py
orangecontrib/earth/widgets/icons/EarthMars.svg
orangecontrib.earth-0.1.4.dist-info/DESCRIPTION.rst
orangecontrib.earth-0.1.4.dist-info/METADATA
orangecontrib.earth-0.1.4.dist-info/RECORD
orangecontrib.earth-0.1.4.dist-info/WHEEL
orangecontrib.earth-0.1.4.dist-info/entry_points.txt
orangecontrib.earth-0.1.4.dist-info/metadata.json
orangecontrib.earth-0.1.4.dist-info/namespace_packages.txt
orangecontrib.earth-0.1.4.dist-info/top_level.txt
