Metadata-Version: 2.0
Name: orangecontrib.earth
Version: 0.1.4
Summary: An implementation of MARS algorithm for Orange.
Home-page: https://bitbucket.org/ales_erjavec/orangecontrib-earth
Author: Bioinformatics Laboratory, FRI UL
Author-email: contact@orange.biolab.si
License: GPLv3
Download-URL: https://pypi.python.org/pypi/orangecontrib.earth
Keywords: mars,earth,multivariate adaptive regression splines,machine learning,orange add-on
Platform: UNKNOWN
Classifier: Environment :: Console
Classifier: Environment :: Plugins
Classifier: Programming Language :: Python
Classifier: License :: OSI Approved :: GNU General Public License v3 or later (GPLv3+)
Classifier: Operating System :: OS Independent
Classifier: Topic :: Scientific/Engineering :: Artificial Intelligence
Classifier: Topic :: Software Development :: Libraries :: Python Modules
Classifier: Intended Audience :: Education
Classifier: Intended Audience :: Science/Research
Classifier: Intended Audience :: Developers
Requires-Dist: Orange (>=2.7)
